bitshares_signing/__init__.py
bitshares_signing/base58.py
bitshares_signing/build_transaction.py
bitshares_signing/config.py
bitshares_signing/graphene_auth.py
bitshares_signing/graphene_signing.py
bitshares_signing/memo.py
bitshares_signing/operations.py
bitshares_signing/rpc.py
bitshares_signing/types.py
bitshares_signing/unit_test.py
bitshares_signing/utilities.py
bitshares_signing/graphenize/asset_create.py
bitshares_signing/graphenize/call_order_update.py
bitshares_signing/graphenize/fee_pool.py
bitshares_signing/graphenize/issue_reserve.py
bitshares_signing/graphenize/limit_orders.py
bitshares_signing/graphenize/liquidity_pools.py
bitshares_signing/graphenize/price_feeds.py
bitshares_signing/graphenize/transfer.py
bitshares_signing-1.3.0.dist-info/METADATA
bitshares_signing-1.3.0.dist-info/WHEEL
bitshares_signing-1.3.0.dist-info/top_level.txt
bitshares_signing-1.3.0.dist-info/RECORD
