Metadata-Version: 2.4
Name: bitshares-signing
Version: 1.3.0
Summary: Lightweight Python library for BitShares
Author: squidKid-deluxe, litepresence
Keywords: bitshares,signing,cryptography
Classifier: Programming Language :: Python :: 3.9
Classifier: Operating System :: POSIX :: Linux
Classifier: Development Status :: 3 - Alpha
Requires-Python: >=3.9
Requires-Dist: websocket-client>=1.2.3
Requires-Dist: secp256k1<=0.13.2
